thorr/__about__.py
thorr/__init__.py
thorr/__main__.py
thorr/cli.py
thorr/core.py
thorr/database.py
thorr/estimate.py
thorr/utils.py
thorr/data/processing.py
thorr/data/retrieval.py
thorr/data_/processing.py
thorr/data_/retrieval.py
thorr/misc_/proj_setup.py
thorr/ml_tools/temperature_estimate.py
thorr/ml_tools/train_model.py
thorr/utils_/__init__.py
thorr/utils_/config.py
thorr/utils_/database.py
thorr/utils_/logger.py
thorr/utils_/misc.py
thorr-1.0.3.dist-info/METADATA
thorr-1.0.3.dist-info/WHEEL
thorr-1.0.3.dist-info/licenses/LICENSE.txt
thorr-1.0.3.dist-info/RECORD
