Metadata-Version: 2.4
Name: thorr
Version: 1.0.3
Summary: THORR - A python package that generates river temperature in a continuous spatiotemporal manner. The name THORR is abbreviated from Thermal History Of Regulated Rivers.
Project-URL: GitHub, https://github.com/UW-SASWE/THORR
Project-URL: Webapp, https://depts.washington.edu/saswe/thorr
Author-email: George Darkwah <gdarkwah@uw.edu>, Faisal Hossain <fhossain@uw.edu>
Maintainer-email: George Darkwah <gdarkwah@uw.edu>
License-Expression: GPL-3.0-or-later
License-File: LICENSE.txt
Keywords: remote sensing,river-temperature,temperature,thermal infrared
Classifier: Development Status :: 4 - Beta
Classifier: Operating System :: OS Independent
Classifier: Programming Language :: Python :: 3
Requires-Python: >=3.10
Requires-Dist: dataretrieval
Requires-Dist: geemap
Requires-Dist: geopandas
Requires-Dist: matplotlib
Requires-Dist: mysql-connector-python
Requires-Dist: numpy
Requires-Dist: pandas
Requires-Dist: psycopg[binary]
Requires-Dist: pycrs
Requires-Dist: rasterio
Requires-Dist: scikit-learn
Requires-Dist: setuptools
Requires-Dist: shapely
Requires-Dist: typer
